{"title": "Kaziprd", "content": "<p>Včera nebo nedávno jsem měl poprvé v životě nasazenou americkou helmu na fotbal, víte, co myslím. Tu originální, která má chránič na bradu. Je to nářez. Těsné jak kunda atraktivní šestnáctky. Se divím, že ti kluci vydrží v tom hrát a trénovat dýl než minutu. Tlačí to na mozek, až se z něj musí nutně stát kaše. Konzistencí, vůbec nepochybuji o tom, že američtí fotbalisté jsou svého druhu mozci na úrovni lorda Newtona.&nbsp;</p><p>Takže když hrají třeba hodinu a půl před publikem, takhle stlačená kaše vysílá signály do noh a oni běhají jak loutky. Strašné divadlo...</p><p>Ale proto je obdivujeme, snášejí příkoří a nesnáze líp než ostatní, a proto jsou ostatně taky tak dobře placeni.</p>", "published": "2020-10-24T18:20:00.013Z", "tags": [], "filename": "/2020/10/kaziprd.html"}