{"title": "Chudý Honza, bohatý John", "content": "<div>Zjistil jsem, že pokud vás trápí bolesti břicha, kožní vyrážky (akné především) nebo migrény, pak je možné, že se jedná o symptomy histaminové intolerance, a tak musíte stůj co stůj podstoupit drastickou dietu, aby se příznaly zmírnily nebo nejlépe odezněly.</div><div>Histamin je důležitý pro správnou funkci mozku a hladké svaloviny, jenže když se ho nahromadí nadbytek, pocítíte ho spíš negativně. Některé ženy bohužel přijdou dočasně o měsíčky, a mohou se tak cítit zmatené, jiné zas schvátí proslulá deprese, nastoupí tupé bolesti hlav a dokonce možná přestanete zdravě spát. U mužů jsou projevy mírnější, protože toho histaminu obvykle tolik nenashromáždí a navíc chlap se spravným přístupem k životu jistě denně ty dva tři kalíšky sladké pálenky polkne, čímž zabrání nekontrolovanému růstu jeho hodnot v organismu.<br />Kdo nechce riskovat a chce předejít nepříjemným symptonům, <strong>neměl by</strong> rozhodně jíst následující potraviny:</div><div><br /><em>Sýry - zrající sýry - gouda, čedar, parmezán, ementál, rokfór, camembert</em><br /><em>Mléčné výrobky - kyselé / acidofilní kefírové mléko, podmáslí, jogurt (i probiotický)</em><br /><em>Ryby a ostatní mořští živočichové po zmrazení a konzervaci</em><br /><em>Zelenina - špenát, lilek, dýně, kvašené zelí, rajčata (kečup)</em><br /><em>Ovoce - ananas, jahody, nektarinky, banány</em><br /><em>Čokoláda - kakao</em></div><div><br /></div><div>a pít následující nápoje:</div><div><br /></div><div><em>červené víno, sekt a kvasinkové pivo</em></div><div><br /></div><div>Jak vidno, stále zbývá spousta lahůdek pro realizaci tužeb bříška. V klidu můžete spořádat např. hrst oříšků, müsli tyčinku, párek s hořčicí a vypít polotučné mléko nebo koktejl se střikem bílého vína.</div><div>Doktoři z celé zeměkoulě svorně tvrdí, že ve zdravém těle sídlí zdravý, kdežto v nezdravém hodně nemocný duch. Pokud mohu soudit podle sebe, dávám jim absolutně za pravdu.</div>", "published": "2016-03-10T21:21:00Z", "tags": [], "filename": "/2016/03/chudy-honza-bohaty-john.html"}