{
  "title": "Den kvantové konstanty",
  "content": "<p>Kdo zná Plancka, ten plesá blahem, neboť dnes si připomínáme číslo 4.14... podstatně zakrouhleně. A já se zas po desítkách let setkal s přítelem z mládí. Je sice úplně zhuntovaný, takřka na odpis, ale stále žije. Nikdo by to nebyl býval řekl. Jsem opravdu rád. Ale zároveň mi to nedá a musím se ptát. Kolik ještě měsíců může tak zničený tvor požít? Půjde nahoru či už jen dolů? A budu za jeho pád odpovědný já, stuprum?!</p>\n<p>&nbsp;</p>\n<p>Radujte se a těšte s námi, neboť jsme ještě neřekli poslední slovo.</p>",
  "published": "2026-04-14T18:35:37.624Z",
  "tags": [],
  "filename": ""
}