{"title": "Nebyl v záložkách", "content": "<div><em>Který velký čin není ve chvíli, kdy jej podnikáme, extrémem? Obyčejným lidem se zdá uskutečnitelným, teprve když je vykonán. Ano, v mém srdci bude kralovat láska se všemi svými zázraky, cítím to podle vzrušení, které se mě zmocňuje. Nebesa mi byla dlužna tuto přízeň. Nezahrnula nadarmo jedinou bytost všemi přednostmi. Mé štěstí bude mne hodno.</em></div><div style=\"text-align:right\">Červený a černý</div>", "published": "2014-09-19T03:55:00Z", "tags": [], "filename": "/2014/09/nebyl-v-zalozkach.html"}