{"title": "Průvan a dopravní problémy jí dokonaly zvedly mandle", "content": "Líbily se mi nekomplikované vztahy, které vládly u nich v rodině. Navíc na sebe nechávala klidně sahat, bohužel jen nahoře. Měla hezky vyvinuté poprsí a její zeměpisný přehled mi vždy bral dech. Chodily jsme spolu bohužel jen dva měsíce, pak se vrátil její přítel z mise v Íráku. Poslední večer před jeho příletem jsme si vyrazili na diskotéku. Tančilo se na stolech, lahve od vína lítaly vzduchem, nahuleno tam bylo za chvíli tak, že jsem skoro plakal. Nebylo mi nejlíp, protože začali rozbíjet okna a židle a všichni příšerně řvali.", "published": "2021-12-29T19:21:00.002Z", "tags": [], "filename": "/2021/12/pruvan-dopravni-problemy-ji-dokonaly.html"}