{"title": "Je to ledabyle oplácaná septimánka", "content": "<p>Nemůžete se pořádně vyspat? Leze vám na nervy váš kluk? Nic nezoufejte. Existuje prověřený plán, který bezpečně vymaže z vašeho života jakéhokoliv škůdce. Mohu vám o něm sdělit podrobnosti, ale taky nemusím, je to na vás. Z mé zkušenosti vím, že ženy, jakkoliv se rády podobně tváří, nejsou tak šťastné jako\nhory, které nevědí o svém štěstí a které na svých vrcholcích dlouho zadržují\npaprsky zapadajícího slunce a nechávají se třeba laskat světlem, které na horách trvá podstatně dýl než v nížině. Ženy mají obvykle určitou jasnou představu o tom, v čem se nacházejí, což je činí poněkud rozumnějšími bytostmi, než jsou třeba páni. Moje poslední buchta je nyní mdlá a chmurná hromádka trosek, která zcela\npotřela tu zářivou a veselou barvu, která kdysi zlatívala svými dráždivými odstíny její tak hebce růžové čelo... stačilo pár let užívání perníku a dojela jak Loprais na duně. Přesto ji všecko napovídalo, že když bude setrvávat ve zle a nectnosti, nevyhnutelně skončí na dlažbě - což se taky bohužel stalo. Nicméně, abychom odlehčili toto tolik těžké téma, připomeňme si, že na světě jsou i holčiny veselé, které nemají sklony k nadměrnému pití a píchání si do žil. Působí v různých sférách života, některé jsou kadeřnice, jiné advokátky, další zas sociální pracovnice. Nejvýraznější z nich je momentálně jedna tmavá květinka, která slyší na jméno Alexandria&nbsp;Ocasio-Cortezová a která zastává jakési velmi důležité místo v Sněmovně reprezentantů Spojených států. Tato Alexandria má kromě velmi vábné figury a vyjadřovacích schopností na úrovni Lao'c taky moc hezké, stále ještě své zuby a taky, jak se říká, duši!&nbsp;</p><p><br /></p><div class=\"separator\" style=\"clear: both; text-align: center;\"><iframe allowfullscreen=\"\" class=\"BLOG_video_class\" height=\"266\" src=\"https://www.youtube.com/embed/tSZcdMCHn2o\" width=\"320\" youtube-src-id=\"tSZcdMCHn2o\"></iframe></div><br /><div class=\"separator\" style=\"clear: both; text-align: center;\"><br /></div><br /><p><br /></p><p>Tady se postavila k ožehavému tématu dnešní doby.&nbsp; K naprosto toxickému jednání ze strany kongresmana Teda Yoha, který ji při nějaké a snad i nějaké další, soukromé, příležitosti naprosto nevhodně urazil.<br />Urazil ji do nekřesťanských pojmů, když byli sami a pak, když po nebi táhly nízké a šedé cáry mračen, urazil ji ještě před vchodem do domu, kde byli její sestřenice, bratranci, neteře a další drobotina, uprostřed squatu rodiny, při krbu krve, tak říkajíc... A to už statečná obránkyně práv neunesla a vzala se za slovo. Za slovo se brát umí, to můžeme mít možnost vidět i v tomhle videu, kde kongresmana doslova rozcupovala na slabiky.</p>", "published": "2023-03-04T19:23:00.059Z", "tags": ["pro samičky"], "filename": "/2023/03/je-to-ledabyle-oplacana-septimanka.html"}