{"title": "Tápající ve tmách", "content": "<div style=\"text-align: center;\">miluji noc torzo černé Venuše</div><div style=\"text-align: center;\">jamesony pihované</div><div style=\"text-align: center;\">s mírným žalem dělím se s ní o krígl</div><div style=\"text-align: center;\"><br /></div><div style=\"text-align: left;\">Nezapomeňte, že miluji ty, kteří se nebojí sestoupit za asfodelovou louku nevědomí, až z útrob vnitřností hnijících břeckou piva, na rtech jména bývalek za oparem mlhy, pojí mě k nim blízkost spříznění, asi jako vaše bradavky pojí vaše nabíječe, jsou pro ně ornými poli, co vadnou rychlostí blesku, ale ve vší tichosti, gravitací shrnovaných pod křídla zdechlin.&nbsp;<br /><br /></div><div style=\"text-align: left;\">Nečekám nikoho, a přesto se stále dívám na dveře, jestli do nich nevstoupí.. nějaká <a href=\"https://lee-banda.blogspot.com\">lee-banda</a>, krasavice ve špinavém prádle, nějaký pořádný brouček k vytrhání křidélek! Brouček z obrazů totiž není opravdový brouček, slova ho zkazila. Nabádám vás znovu, přijdete-li k mým dveřím, nevstupujte.</div><div style=\"text-align: center;\"><br /></div><div style=\"text-align: center;\"><br /></div><div style=\"text-align: center;\"><br /></div><div style=\"text-align: center;\"><br /></div><div><p class=\"MsoBodyTextIndent2\"></p><div style=\"text-align: center;\">Dva životy, okamžik, úplnost, blaženství</div><div style=\"text-align: center;\">hektolitry vína, romantických seriálů a koitů,</div><div style=\"text-align: center;\">na nádraží zamávala a já, který jel dál,</div><div style=\"text-align: center;\">jsem pochopil, že už ji nikdy nespatřím,</div><p></p><p class=\"MsoBodyTextIndent2\"><o:p></o:p></p><div style=\"text-align: center;\">že i kdybych za ní šel, šel bych za ní jako mrtvý</div></div><div style=\"text-align: center;\">že i kdyby se vrátila,</div><div style=\"text-align: center;\">vrátila by se leda z onoho světa</div><div style=\"text-align: center;\"><br /></div><div style=\"text-align: center;\"><br /></div><div style=\"text-align: center;\"><br /></div><div style=\"text-align: center;\"><br /></div><div style=\"text-align: center;\"><br /></div><div style=\"text-align: center;\">Podzime, podzime,</div><div style=\"text-align: center;\">rzivou sněti krve potřísněný,</div><div style=\"text-align: center;\">plesová vráno na snopu,</div><div style=\"text-align: center;\">přeletíš námi bez zvuku,</div><div style=\"text-align: center;\">jako semeno je bez slova.</div><div style=\"text-align: center;\"><br /></div><div style=\"text-align: center;\"><br /></div><div style=\"text-align: center;\"><br /></div><div style=\"text-align: center;\"><br /></div><div style=\"text-align: center;\"><br /></div><div style=\"text-align: center;\"><br /></div><div style=\"text-align: center;\">Byla k zulíbání</div><div style=\"text-align: center;\">a hned ji taky zlíbal</div><div style=\"text-align: center;\">její všecky potlačené slzy</div><div style=\"text-align: center;\">proudily vzhůru k úsměvu</div><div style=\"text-align: center;\"><br /></div><div style=\"text-align: center;\">když nazítří odcházela</div><div style=\"text-align: center;\">jitro ji tisklo do zad</div><div style=\"text-align: center;\">vzpomínky stehen</div><div style=\"text-align: center;\"><br /></div><div style=\"text-align: center;\"><br /></div><div style=\"text-align: center;\"><br /></div>", "published": "2020-08-15T18:21:00.110Z", "tags": [], "filename": "/2020/08/tapajici-ve-tmach.html"}