{"title": "Dorozumívala se prsy", "content": "<div><em>nevím kolik lahví</em></div><div><em>piva jsem</em></div><div><em>zkonzumoval,</em></div><div><em>zatímco jsem čekal, že se věci samy</em></div><div><em>vyřeší.</em></div><div><em>nevím kolik lahví vína a whisky</em></div><div><em>a piva</em></div><div><em>hlavně piva</em></div><div><em>jsem zkonzumoval po</em></div><div><em>rozchodech se ženami</em></div><div><br /></div><div>ženská vydrží</div><div>když my šílíme</div><div>svěží jak jarní kvítí</div><div>nese se na podpatcích</div><div>do bungalovu</div><div>našlapuje jak kočka</div><div>kroky se nakonec ozvou</div><div>vždy příliš pozdě</div><div>jen aby mohla u dveří</div><div>seřvat na tři doby opilce</div><div>který má ledový žaludek v krku</div><div><br /></div><div>ženská vydrží</div><div>žije o sedm a půl roku déle</div><div>než muž a pije hrozně málo piva</div><div>protože ví, že jde</div><div>na tloušťku</div><div>cosi ji napovídá, že</div><div>řeky a moře piv už vůbec</div><div>nemají dna, ba ani</div><div>nemají koryt, prostě</div><div>tečou bez přestání,</div><div>stékají do povodí</div><div>a tam se rodí další</div><div><br /></div><div>v rádiu hrajou písničku</div><div>o pivu</div><div>a ona tančí</div><div>a směje se</div><div>s primitivem</div><div>stěny se točí</div><div>a ona padá</div><div>a pivo je to jediný co jí nakonec zbývá</div>", "published": "2016-05-21T21:21:00Z", "tags": [], "filename": "/2016/05/dorozumivala-se-prsy.html"}