{"title": "Suma na dosah ruky", "content": "<div>Kráska měla bezmocný vzhled a pohromadě s chudobou ducha nevypadala její budoucnost zrovna zářívě. Ačkoliv řeč prošpikováná hatmatilkou jí dělala v očích cizinců chytřejší, španělština to nebyla. Jak jsme již předeslali, patřila k nejkrásnějším Antilankám. Sestry, obě v plném květu, vypadaly jako dvě rozjívené klisny, se kterými to háže.<br />Beznadějný byl případ otce, hrdiny občanských válek z minulého století: poznali ho všichni, hned jak se vyklonil z okénka automobilu a zdravil bílým kloboukem. Na nose zlaté brýle a když vystoupil, každý si všiml obleku pšeničné barvy s trochu divným střihem.</div><div><br /></div><div>Jsem dneska měl tak rozdrbané prsty z betonu, že mi noťas nechtěl vzít otisky prstů, tak jsem musel zadávat heslo ručně, he.</div><div><br /></div><div>Na National geographicu je brutální fotka dne, hejno kobylek na Madagaskaru.</div>", "published": "2014-11-20T04:27:00Z", "tags": [], "filename": "/2014/11/suma-na-dosah-ruky.html"}