{"title": "Buď mýma očima", "content": "<div>Mnohá světla svíček zhasla úplně, jiná čadila a páchla a mastnota z nich kapala na podlahu.</div><div><br /></div><div>Bohyně smíchu mi nakázala, abych byl vtipný. Jenže nedokážu cvičit, jak někdo píská. Byl jsem v baru teďka. Tam oblíbená barmanka z Portorika rozkládá o svých chlapech. Má děcko, když ji bylo šestnáct, teď je ji šestatřicet. Chce najít šarmantního typa, který ji bude prokazovat služby vztahu. Takové to: když chceš někam jít, vem mě s sebou.</div><div>Chce, aby ji dlouze hleděl do očí, říkal, že je krásná atd.</div><div>Ona je rozhodně s půvaby udělaná. Ale žije mimo realitu.</div><div>Nechce sex, chce vážný vztah.</div><div>Takový přístup nemá v jednadvacátém století šanci přežít. Nevěšte si bulíky na nosíčky. Ani si nevěšte piercingy mezi pysky, protože kluci dneska už poznají fejky, kočíčí zlato mezi osmadvaceti karáty.</div><div>Po cestě domů jsem narazil na tři krysí hovínka. Úplně mě to vykolejilo. Možná nebyly krysí, ale třeba veverčí, jichž je tu habaděj.</div>", "published": "2016-01-05T21:21:00Z", "tags": [], "filename": "/2016/01/bud-myma-ocima.html"}