{"title": "Hodil si mincí", "content": "<div>\"Pojď šukat,\" ozvalo se z kuchyně, <span style=\"background-color:transparent\">ta slova slyšel, porozuměl jejich významu, avšak rázem mu vylétla z paměti.</span> <span style=\"background-color:transparent\">Měl namířeno za Sárou. Ta není tak držkatá.</span></div><div><span style=\"background-color:transparent\">Když dorazil za tou druhou, zrovna vysávala.</span> <span style=\"background-color:transparent\"><span style=\"background-color:transparent\">Z okna vanul vítr přinášející vůni sexu a ledabyle si pohrával s pramínky vlasů, které vyklouzly Sáře na šíji z pevně zapleteného copu.</span></span></div>", "published": "2019-05-17T20:01:00Z", "tags": [], "filename": "/2019/05/hodil-si-minci.html"}