{"title": "Skutečnost je zkomolená", "content": "<div><span style=\"color:#fff;background-color:#000\"><em><span style=\"text-align:center\">Požárem plálo to v hlavě</span></em></span><br style=\"color:#27292b;text-align:center\"><span style=\"color:#fff;background-color:#000\"><em><span style=\"text-align:center\">a vášeň zmítala těly.</span></em></span><br style=\"color:#27292b;text-align:center\"><span style=\"color:#fff;background-color:#000\"><em><span style=\"text-align:center\">A naše ruce se chvěly</span></em></span><br style=\"color:#27292b;text-align:center\"><span style=\"color:#fff;background-color:#000\"><em><span style=\"text-align:center\">nedočkavě.</span></em></span></div>", "published": "2017-07-02T21:21:00Z", "tags": [], "filename": "/2017/07/skutecnost-je-zkomolena.html"}