{"title": "Je to maska prasete přišitá k tváři", "content": "<p>&nbsp;</p><br style=\"background-color: #202124; color: #e8eaed; font-family: Roboto, Arial, sans-serif; font-size: 16px; font-variant-ligatures: none; letter-spacing: 0.1px; white-space: pre-wrap;\" />Vždyť jsem žil celej život jako prase a taky mezi prasatama. Já si vzpomenu na každý dobrý slovo, co jsem kdy slyšel, tak jich bylo málo.", "published": "2023-02-03T19:23:00.001Z", "tags": [], "filename": "/2023/02/je-to-maska-prasete-prisita-k-tvari.html"}